README.md
setup.cfg
setup.py
jv_toolbox/__init__.py
jv_toolbox/decorators.py
jv_toolbox/functions.py
jv_toolbox.egg-info/PKG-INFO
jv_toolbox.egg-info/SOURCES.txt
jv_toolbox.egg-info/dependency_links.txt
jv_toolbox.egg-info/requires.txt
jv_toolbox.egg-info/top_level.txt