Metadata-Version: 2.1
Name: jv-toolbox
Version: 0.0.1
Summary: Testing installation of Package
Home-page: https://github.com/jgvlk/toolbox_project
Author: Jonathan Vlk
Author-email: jvlk@westmonroe.com
License: MIT
Download-URL: https://github.com/jgvlk/toolbox_project/archive/refs/tags/0.0.1.tar.gz
Project-URL: Bug Tracker, https://github.com/jgvlk/toolbox_project/issues
Keywords: pypi,jv_toolbox,tutorial
Platform: UNKNOWN
Classifier: Development Status :: 3 - Alpha
Classifier: Intended Audience :: Developers
Classifier: Topic :: Software Development :: Documentation
Classifier: License :: OSI Approved :: MIT License
Classifier: Programming Language :: Python :: 3
Classifier: Programming Language :: Python :: 3.7
Classifier: Programming Language :: Python :: 3.8
Classifier: Programming Language :: Python :: 3.9
